{
    "keep": {
        "days": true,
        "amount": 14
    },
    "auditLog": "E:\\PROJECTS\\Woptio By Imran Vai Kolaroa\\toolinger\\backend\\logs\\winston\\successes\\.5b572df80b3e46ebb1a46e0b2dde6d3ba494eb64-audit.json",
    "files": [
        {
            "date": 1755945953424,
            "name": "E:\\PROJECTS\\Woptio By Imran Vai Kolaroa\\toolinger\\backend\\logs\\winston\\successes\\Tools-X-2025-23-08-16-success.log",
            "hash": "c698fceceb0f5ca3299193bbd20c31d35457fb237860390c7b89b23c0d178cc9"
        },
        {
            "date": 1755965689574,
            "name": "E:\\PROJECTS\\Woptio By Imran Vai Kolaroa\\toolinger\\backend\\logs\\winston\\successes\\Tools-X-2025-23-08-22-success.log",
            "hash": "e409aa2268b2de8e67cea588ce1aec372be1de874129962008c49797ab3a416f"
        },
        {
            "date": 1756007357658,
            "name": "E:\\PROJECTS\\Woptio By Imran Vai Kolaroa\\toolinger\\backend\\logs\\winston\\successes\\Tools-X-2025-24-08-09-success.log",
            "hash": "f7f34e595f91bea93ce53e7dfa406d4b1f57a6204ea0e5bdb11e51b3a63ad3e5"
        },
        {
            "date": 1756008210942,
            "name": "E:\\PROJECTS\\Woptio By Imran Vai Kolaroa\\toolinger\\backend\\logs\\winston\\successes\\Tools-X-2025-24-08-10-success.log",
            "hash": "24a7d466147ee7425dd2970b7aaf2866f749fc09d7a365e28063c1b2766b2abe"
        },
        {
            "date": 1756016668327,
            "name": "E:\\PROJECTS\\Woptio By Imran Vai Kolaroa\\toolinger\\backend\\logs\\winston\\successes\\Tools-X-2025-24-08-12-success.log",
            "hash": "db331ced88d17f13c89f58eda5e3febbab51fe14a1ce0b26a4e2ef706f6aa267"
        },
        {
            "date": 1756019207004,
            "name": "E:\\PROJECTS\\Woptio By Imran Vai Kolaroa\\toolinger\\backend\\logs\\winston\\successes\\Tools-X-2025-24-08-13-success.log",
            "hash": "667b03cbc42604adeb3e612d3fc71000fc356213533175cc6c69985fdb06b363"
        },
        {
            "date": 1756144024485,
            "name": "E:\\PROJECTS\\Woptio By Imran Vai Kolaroa\\toolinger\\backend\\logs\\winston\\successes\\Tools-X-2025-25-08-23-success.log",
            "hash": "f8a857b5e2f8662a2264e7ca1cc148f43e8058065db645f396bd124627df4696"
        },
        {
            "date": 1756147073234,
            "name": "E:\\PROJECTS\\Woptio By Imran Vai Kolaroa\\toolinger\\backend\\logs\\winston\\successes\\Tools-X-2025-26-08-00-success.log",
            "hash": "0804066e5257dcf5e16ad8533bf2a251235e08792e08b32a638c5e735bf721e6"
        },
        {
            "date": 1756148538544,
            "name": "E:\\PROJECTS\\Woptio By Imran Vai Kolaroa\\toolinger\\backend\\logs\\winston\\successes\\Tools-X-2025-26-08-01-success.log",
            "hash": "368887df870bd4d6df82768ca7fece0bee7f0c221e298dd6d1efcf436e33b199"
        },
        {
            "date": 1756152374547,
            "name": "E:\\PROJECTS\\Woptio By Imran Vai Kolaroa\\toolinger\\backend\\logs\\winston\\successes\\Tools-X-2025-26-08-02-success.log",
            "hash": "1d5c6d8252bb0ab77c97f6190f3886f0bb11c4de1aea3ffd6cce25cc11a156b8"
        },
        {
            "date": 1756182372938,
            "name": "E:\\PROJECTS\\Woptio By Imran Vai Kolaroa\\toolinger\\backend\\logs\\winston\\successes\\Tools-X-2025-26-08-10-success.log",
            "hash": "453cde601cb05ebf89f411d8c2e8e90f003bc98b86ff7b9e5b9387f5b19b42d2"
        },
        {
            "date": 1756360798523,
            "name": "E:\\PROJECTS\\Woptio By Imran Vai Kolaroa\\toolinger\\backend\\logs\\winston\\successes\\Tools-X-2025-28-08-11-success.log",
            "hash": "bff3c79b492925ad3fc7878bc829433b2c0df8a6d9cb2eded5b083f6907b38ac"
        },
        {
            "date": 1756360804989,
            "name": "E:\\PROJECTS\\Woptio By Imran Vai Kolaroa\\toolinger\\backend\\logs\\winston\\successes\\Tools-X-2025-28-08-12-success.log",
            "hash": "2bf83750fcb2998123c574cf683d6848791e8ffe23ceaa49fa2bfc622836a2fe"
        },
        {
            "date": 1756455631697,
            "name": "E:\\PROJECTS\\Woptio By Imran Vai Kolaroa\\toolinger\\backend\\logs\\winston\\successes\\Tools-X-2025-29-08-14-success.log",
            "hash": "9a80f3aaf279c7380110857268be411a93c9cba78cafd4c2393ee8d9df3c511e"
        },
        {
            "date": 1756473697372,
            "name": "E:\\PROJECTS\\Woptio By Imran Vai Kolaroa\\toolinger\\backend\\logs\\winston\\successes\\Tools-X-2025-29-08-19-success.log",
            "hash": "0453478a8d3a1013fe5fc5e3f0a2476348888b30892459f2458c1a5de4570541"
        },
        {
            "date": 1756478452971,
            "name": "E:\\PROJECTS\\Woptio By Imran Vai Kolaroa\\toolinger\\backend\\logs\\winston\\successes\\Tools-X-2025-29-08-20-success.log",
            "hash": "04b307ad8c73267057145a3831761edb88b4b6db217f59cc5da97b29f7fa4853"
        },
        {
            "date": 1756526899253,
            "name": "E:\\PROJECTS\\Woptio By Imran Vai Kolaroa\\toolinger\\backend\\logs\\winston\\successes\\Tools-X-2025-30-08-10-success.log",
            "hash": "22178133d86dc8e79508058b70aa4c429c70ea5383503b40056f03b82ab5d299"
        },
        {
            "date": 1756531855561,
            "name": "E:\\PROJECTS\\Woptio By Imran Vai Kolaroa\\toolinger\\backend\\logs\\winston\\successes\\Tools-X-2025-30-08-11-success.log",
            "hash": "b3e823dfd9e8cf9503475f493723779db97133feae41b6368f2f7637b4b1e5ab"
        },
        {
            "date": 1756537886055,
            "name": "E:\\PROJECTS\\Woptio By Imran Vai Kolaroa\\toolinger\\backend\\logs\\winston\\successes\\Tools-X-2025-30-08-13-success.log",
            "hash": "d473538f67565b824bb810b7fdb8a1e396d75874daf56c7832f425219df74879"
        },
        {
            "date": 1756555442788,
            "name": "E:\\PROJECTS\\Woptio By Imran Vai Kolaroa\\toolinger\\backend\\logs\\winston\\successes\\Tools-X-2025-30-08-18-success.log",
            "hash": "1ce454ab816bb555a84ffee9e102e99f1a6f391e7f3e49ffb0c931edb021e063"
        },
        {
            "date": 1756563350187,
            "name": "E:\\PROJECTS\\Woptio By Imran Vai Kolaroa\\toolinger\\backend\\logs\\winston\\successes\\Tools-X-2025-30-08-20-success.log",
            "hash": "2f6f8371f10f35c635f77e25988861bf7838af0f5ebf071c3df0c322f78c3a64"
        },
        {
            "date": 1756566602413,
            "name": "E:\\PROJECTS\\Woptio By Imran Vai Kolaroa\\toolinger\\backend\\logs\\winston\\successes\\Tools-X-2025-30-08-21-success.log",
            "hash": "c3d699fab3b591c0568e49f38b814b56d4847d1fd519208d614db731271c6371"
        },
        {
            "date": 1756609080784,
            "name": "E:\\PROJECTS\\Woptio By Imran Vai Kolaroa\\toolinger\\backend\\logs\\winston\\successes\\Tools-X-2025-31-08-08-success.log",
            "hash": "31c4000dfd216b70138fe853e0be1ec9b0f7e5e35367158d98dda92c7b74032f"
        },
        {
            "date": 1756609213757,
            "name": "E:\\PROJECTS\\Woptio By Imran Vai Kolaroa\\toolinger\\backend\\logs\\winston\\successes\\Tools-X-2025-31-08-09-success.log",
            "hash": "85d6a1705995e4d045fca5d946dba0dcb0d1c696d1e0b8bba9c5dc48b4a4e5e3"
        }
    ],
    "hashType": "sha256"
}